{
  "folder": "CUKsadcWW9Xjh3at",
  "name": "Ataques Múltiplos",
  "type": "class_ability",
  "_id": "6P5yyNcRTCMygF23",
  "img": "systems/olddragon2e/assets/icons/kit.svg",
  "system": {
    "description": "<p>Ganha um <strong>segundo ataque</strong> com a mesma Base de Ataque.</p>",
    "level": 6,
    "level3": "",
    "level6": "",
    "level10": "",
    "rogue_talents": [],
    "daily_uses": {
      "1": 0,
      "2": 0,
      "3": 0,
      "4": 0,
      "5": 0,
      "6": 0,
      "7": 0,
      "8": 0,
      "9": 0,
      "10": 0,
      "11": 0,
      "12": 0,
      "13": 0,
      "14": 0,
      "15": 0
    }
  },
  "effects": [],
  "flags": {},
  "_stats": {
    "compendiumSource": null,
    "duplicateSource": null,
    "coreVersion": "13.342",
    "systemId": "olddragon2e",
    "systemVersion": "This is auto replaced",
    "createdTime": 0,
    "modifiedTime": 0,
    "lastModifiedBy": "swsdbuildtool",
    "exportSource": null
  },
  "sort": 300000,
  "ownership": {
    "default": 0
  },
  "_key": "!items!6P5yyNcRTCMygF23"
}
